doxieapi/__init__.py
doxieapi/__main__.py
doxieapi/api.py
doxieapi/ssdp.py
doxieapi-0.1.2.dist-info/LICENSE
doxieapi-0.1.2.dist-info/METADATA
doxieapi-0.1.2.dist-info/WHEEL
doxieapi-0.1.2.dist-info/top_level.txt
doxieapi-0.1.2.dist-info/RECORD
