Metadata-Version: 2.1
Name: doxieapi
Version: 0.1.2
Summary: Library for downloading scans from a Doxie Go Wi-Fi document scanner
Home-page: https://github.com/davea/doxieapi/
Author: Dave Arter
Author-email: pypi@davea.me
License: LICENSE
Keywords: doxie document scanner
Platform: UNKNOWN
Requires-Python: >=3.4
Requires-Dist: requests
